openslides_saml/__init__.py
openslides_saml/apps.py
openslides_saml/exceptions.py
openslides_saml/saml_settings.json.tpl
openslides_saml/settings.py
openslides_saml/urls.py
openslides_saml/views.py
openslides_saml/management/__init__.py
openslides_saml/management/commands/__init__.py
openslides_saml/management/commands/create-saml-settings.py
openslides_saml/static/js/openslides_saml/base.js
openslides_saml/static/js/openslides_saml/site.js
openslides_saml-1.0.dist-info/METADATA
openslides_saml-1.0.dist-info/RECORD
openslides_saml-1.0.dist-info/WHEEL
openslides_saml-1.0.dist-info/entry_points.txt
openslides_saml-1.0.dist-info/top_level.txt
