Metadata-Version: 2.1
Name: openslides-saml
Version: 1.0
Summary: OpenSlides SAML Plugin
Home-page: https://github.com/OpenSlides/openslides-saml
Author: Authors of OpenSlides SAML Plugin, see AUTHORS
Author-email: support@openslides.org
License: MIT
Keywords: OpenSlides
Platform: UNKNOWN
Classifier: Development Status :: 5 - Production/Stable
Classifier: Environment :: Plugins
Classifier: Environment :: Web Environment
Classifier: Framework :: Django
Classifier: License :: OSI Approved :: MIT License
Classifier: Operating System :: OS Independent
Classifier: Programming Language :: Python :: 3
Classifier: Programming Language :: Python :: 3.4
Classifier: Programming Language :: Python :: 3.5
Classifier: Programming Language :: Python :: 3.6
Requires-Dist: openslides (<2.3,>=2.2)
Requires-Dist: python3-saml (>=1.3.0)
